minio_console/__init__.py
minio_console/buckets.py
minio_console/client.py
minio_console/policies.py
minio_console/users.py
minio_console-0.1.1.dist-info/LICENSE
minio_console-0.1.1.dist-info/METADATA
minio_console-0.1.1.dist-info/WHEEL
minio_console-0.1.1.dist-info/top_level.txt
minio_console-0.1.1.dist-info/RECORD
